rocket_toolkit/__init__.py
rocket_toolkit/config.py
rocket_toolkit/default_config.json
rocket_toolkit/cli/__init__.py
rocket_toolkit/cli/main.py
rocket_toolkit/core/__init__.py
rocket_toolkit/core/fin_temperature_tracker.py
rocket_toolkit/core/flight_simulator.py
rocket_toolkit/core/stability_analyzer.py
rocket_toolkit/core/thermal_analyzer.py
rocket_toolkit/core/thermal_data.py
rocket_toolkit/core/trajectory_optimizer.py
rocket_toolkit/geometry/__init__.py
rocket_toolkit/geometry/component_manager.py
rocket_toolkit/geometry/materials.py
rocket_toolkit/geometry/rocket_fin.py
rocket_toolkit/models/__init__.py
rocket_toolkit/models/atmosphere_model.py
rocket_toolkit/models/material_comparison_example.py
rocket_toolkit/plotting/__init__.py
rocket_toolkit/plotting/fin_animation.py
rocket_toolkit-0.2.1.dist-info/METADATA
rocket_toolkit-0.2.1.dist-info/WHEEL
rocket_toolkit-0.2.1.dist-info/entry_points.txt
rocket_toolkit-0.2.1.dist-info/top_level.txt
rocket_toolkit-0.2.1.dist-info/RECORD
