Metadata-Version: 2.4
Name: rocket_toolkit
Version: 0.2.1
Summary: Rocket analysis tools with interactive CLI menu
Author-email: Jesper Meijerink <jnmeijerink@tudelft.nl>
License: MIT
Project-URL: Homepage, https://github.com/J1mmortal/rocket-analysis-toolkit
Requires-Python: >=3.10
Requires-Dist: numpy
Requires-Dist: matplotlib
Requires-Dist: pandas
Requires-Dist: isacalc
